sensirion_shdlc_sensorbridge/__init__.py
sensirion_shdlc_sensorbridge/definitions.py
sensirion_shdlc_sensorbridge/device.py
sensirion_shdlc_sensorbridge/device_errors.py
sensirion_shdlc_sensorbridge/firmware_image.py
sensirion_shdlc_sensorbridge/i2c_errors.py
sensirion_shdlc_sensorbridge/i2c_proxy.py
sensirion_shdlc_sensorbridge/types.py
sensirion_shdlc_sensorbridge/version.py
sensirion_shdlc_sensorbridge/commands/__init__.py
sensirion_shdlc_sensorbridge/commands/analog_measurement.py
sensirion_shdlc_sensorbridge/commands/baudrate.py
sensirion_shdlc_sensorbridge/commands/blink.py
sensirion_shdlc_sensorbridge/commands/device_information.py
sensirion_shdlc_sensorbridge/commands/firmware_update.py
sensirion_shdlc_sensorbridge/commands/get_version.py
sensirion_shdlc_sensorbridge/commands/i2c_repeated_transceive.py
sensirion_shdlc_sensorbridge/commands/i2c_scan.py
sensirion_shdlc_sensorbridge/commands/i2c_transceive.py
sensirion_shdlc_sensorbridge/commands/port_voltage_on_off.py
sensirion_shdlc_sensorbridge/commands/read_buffer.py
sensirion_shdlc_sensorbridge/commands/set_i2c_frequency.py
sensirion_shdlc_sensorbridge/commands/set_port_voltage.py
sensirion_shdlc_sensorbridge/commands/slave_address.py
sensirion_shdlc_sensorbridge/commands/spi_config.py
sensirion_shdlc_sensorbridge/commands/spi_transceive.py
sensirion_shdlc_sensorbridge/commands/stop_repeated_transceive.py
sensirion_shdlc_sensorbridge-0.2.0.dist-info/LICENSE
sensirion_shdlc_sensorbridge-0.2.0.dist-info/METADATA
sensirion_shdlc_sensorbridge-0.2.0.dist-info/WHEEL
sensirion_shdlc_sensorbridge-0.2.0.dist-info/top_level.txt
sensirion_shdlc_sensorbridge-0.2.0.dist-info/RECORD
